{
  "version": "8ed3a9bb26b3782208a6151f8ac1d0ce",
  "data": {
    "featured_shops": null,
    "campaign_bottom_visual": {
      "start": 1608998400,
      "end": 1641225600,
      "banner_image": "3dfb3bb0c7b564a31ed3de9cc73aebd1",
      "data": {
        "image_mobile": "3dfb3bb0c7b564a31ed3de9cc73aebd1",
        "image_ratio_pc": 75,
        "image_ratio": 26.666667,
        "image_pc": "caac7a687a91bac9d2619b406a7d3a70"
      }
    },
    "featured_products": {
      "header_text_color": "#ffffff",
      "items": [
        {
          "itemid": 4308391777,
          "welcome_package_info": null,
          "liked": null,
          "recommendation_info": null,
          "bundle_deal_info": null,
          "price_max_before_discount": 36500000,
          "image": "3578ce5ac446faaac78db04463052298",
          "recommendation_algorithm": null,
          "is_cc_installment_payment_eligible": true,
          "shopid": 52377417,
          "can_use_wholesale": false,
          "group_buy_info": null,
          "reference_item_id": "",
          "currency": "SGD",
          "raw_discount": 27,
          "show_free_shipping": false,
          "video_info_list": [],
          "images": [
            "3578ce5ac446faaac78db04463052298",
            "909260c8b2e8c77847c82c695b912be0",
            "36aa252c308195308fd32058ad681ccc",
            "0ddf4e1d406df9a09bda70ab0f35e30f",
            "d38ea0ec93f3bd5bc7793ab33d710abe",
            "6d9f4f39bba757010830126c4442a8fa"
          ],
          "is_preferred_plus_seller": false,
          "price_before_discount": 36500000,
          "is_category_failed": false,
          "show_discount": 27,
          "cmt_count": 6153,
          "view_count": 61295,
          "catid": 8,
          "voucher_info": null,
          "upcoming_flash_sale": null,
          "is_official_shop": false,
          "brand": "",
          "price_min": 26500000,
          "liked_count": 11327,
          "can_use_bundle_deal": false,
          "show_official_shop_label": false,
          "coin_earn_label": null,
          "price_min_before_discount": 36500000,
          "cb_option": 0,
          "sold": 1841,
          "stock": 85,
          "status": 1,
          "price_max": 26500000,
          "add_on_deal_info": {
            "add_on_deal_id": 2189751,
            "add_on_deal_label": "Add-on Deal",
            "sub_type": 0
          },
          "is_group_buy_item": null,
          "flash_sale": null,
          "price": 26500000,
          "shop_location": "Singapore",
          "item_rating": {
            "rating_star": 4.924265,
            "rating_count": [
              6154,
              24,
              11,
              48,
              244,
              5827
            ],
            "rcount_with_image": 2462,
            "rcount_with_context": 3650
          },
          "show_official_shop_label_in_title": false,
          "tier_variations": [
            {
              "images": [],
              "properties": [],
              "type": 0,
              "name": "",
              "options": [
                ""
              ]
            }
          ],
          "is_adult": false,
          "can_use_cod": null,
          "discount": "27%",
          "flag": 524288,
          "is_non_cc_installment_payment_eligible": false,
          "has_lowest_price_guarantee": false,
          "has_group_buy_stock": null,
          "preview_info": null,
          "welcome_package_type": 0,
          "exclusive_price_info": null,
          "name": "Apple Airpods Pro (Local Set)",
          "ctime": 1574630470,
          "wholesale_tier_list": [],
          "show_shopee_verified_label": true,
          "show_official_shop_label_in_normal_position": null,
          "item_status": "normal",
          "shopee_verified": true,
          "hidden_price_display": null,
          "size_chart": null,
          "item_type": 0,
          "shipping_icon_type": null,
          "label_ids": [
            1000012,
            1000055,
            1000035,
            1000036,
            1000075,
            1000092,
            13,
            1001261,
            1001268
          ],
          "service_by_shopee_flag": null,
          "badge_icon_type": 0,
          "historical_sold": 15580,
          "transparent_background_image": "26f99fc58cdb6126c76e3b19fd1fdea7"
        },
        {
          "itemid": 6506237358,
          "welcome_package_info": null,
          "liked": null,
          "recommendation_info": null,
          "bundle_deal_info": null,
          "price_max_before_discount": 48900000,
          "image": "47fe734e00191d983fd370a644148cf7",
          "recommendation_algorithm": null,
          "is_cc_installment_payment_eligible": true,
          "shopid": 82738335,
          "can_use_wholesale": false,
          "group_buy_info": null,
          "reference_item_id": "",
          "currency": "SGD",
          "raw_discount": 14,
          "show_free_shipping": false,
          "video_info_list": [],
          "images": [
            "47fe734e00191d983fd370a644148cf7",
            "27a167f9b95046b766b98ff47c56df15",
            "5a70753032cd1ec97c171f55be775f92",
            "7e9fc42db43ff07f7fb6f033198fcae8",
            "002432d29c37dd0ad1302b2161f76ef6",
            "3d8163948187f8b050a102bdfb7e0ed9",
            "733c0f82a9d6c78e6a5b52b994c052bd",
            "ee799c67e49a4df0d4c4f0497638366b"
          ],
          "is_preferred_plus_seller": false,
          "price_before_discount": 48900000,
          "is_category_failed": false,
          "show_discount": 14,
          "cmt_count": 2882,
          "view_count": 34185,
          "catid": 20153,
          "voucher_info": null,
          "upcoming_flash_sale": null,
          "is_official_shop": false,
          "brand": "Nintendo Switch",
          "price_min": 41900000,
          "liked_count": 4822,
          "can_use_bundle_deal": false,
          "show_official_shop_label": false,
          "coin_earn_label": null,
          "price_min_before_discount": 48900000,
          "cb_option": 0,
          "sold": 494,
          "stock": 156,
          "status": 1,
          "price_max": 41900000,
          "add_on_deal_info": {
            "add_on_deal_id": 2300834,
            "add_on_deal_label": "Add-on Deal",
            "sub_type": 0
          },
          "is_group_buy_item": null,
          "flash_sale": null,
          "price": 41900000,
          "shop_location": "Singapore",
          "item_rating": {
            "rating_star": 4.956612,
            "rating_count": [
              2882,
              2,
              9,
              18,
              57,
              2796
            ],
            "rcount_with_image": 686,
            "rcount_with_context": 1086
          },
          "show_official_shop_label_in_title": false,
          "tier_variations": [
            {
              "images": [
                "06880c1f4130378e72583f25098fe8d8",
                "69980c970df67a42aefa5216f9509cec",
                "5a70753032cd1ec97c171f55be775f92",
                "7e9fc42db43ff07f7fb6f033198fcae8",
                "80f2fe2817be51e0e754beb2abf8c219"
              ],
              "properties": [],
              "type": 0,
              "name": "Warranty/Model",
              "options": [
                "Neon Gen 2 (QS)",
                "Grey Gen 2 (QS)",
                "Neon Gen 2 (MX)",
                "Grey Gen 2 (MX)",
                "Animal Gen 2 (MX)"
              ]
            }
          ],
          "is_adult": false,
          "can_use_cod": null,
          "discount": "14%",
          "flag": 524288,
          "is_non_cc_installment_payment_eligible": false,
          "has_lowest_price_guarantee": false,
          "has_group_buy_stock": null,
          "preview_info": null,
          "welcome_package_type": 0,
          "exclusive_price_info": null,
          "name": "Nintendo Switch Console System Gen 2 Latest Model + Free Screen Protector (1 Year Local Singapore Warranty)",
          "ctime": 1573381544,
          "wholesale_tier_list": [],
          "show_shopee_verified_label": true,
          "show_official_shop_label_in_normal_position": null,
          "item_status": "normal",
          "shopee_verified": true,
          "hidden_price_display": null,
          "size_chart": null,
          "item_type": 0,
          "shipping_icon_type": null,
          "label_ids": [
            1000012,
            1000055,
            1000035,
            1000067,
            1000075,
            1001261,
            1001268
          ],
          "service_by_shopee_flag": null,
          "badge_icon_type": 0,
          "historical_sold": 6588,
          "transparent_background_image": "71857af8b23cac757290f2a58b8e4205"
        },
        {
          "itemid": 6157181712,
          "welcome_package_info": null,
          "liked": null,
          "recommendation_info": null,
          "bundle_deal_info": null,
          "price_max_before_discount": 153900000,
          "image": "78b24eb0ba2d73da86972d154d7bc127",
          "recommendation_algorithm": null,
          "is_cc_installment_payment_eligible": true,
          "shopid": 52377417,
          "can_use_wholesale": false,
          "group_buy_info": null,
          "reference_item_id": "",
          "currency": "SGD",
          "raw_discount": 17,
          "show_free_shipping": false,
          "video_info_list": [],
          "images": [
            "78b24eb0ba2d73da86972d154d7bc127",
            "b08b46014aa1f8018cfc9462e4b6d988",
            "565e9f1b65c5c1f128e37c70efea7129",
            "115c0af098e8d9da6ec1b98e4bdde101",
            "101ff81c4f496104e1ebc1e8c2e3d50a",
            "3e97ce6156d2fda063c2514caeafcd80"
          ],
          "is_preferred_plus_seller": false,
          "price_before_discount": 129900000,
          "is_category_failed": false,
          "show_discount": 17,
          "cmt_count": 283,
          "view_count": 37825,
          "catid": 8,
          "voucher_info": null,
          "upcoming_flash_sale": null,
          "is_official_shop": false,
          "brand": "",
          "price_min": 107900000,
          "liked_count": 884,
          "can_use_bundle_deal": false,
          "show_official_shop_label": false,
          "coin_earn_label": null,
          "price_min_before_discount": 129900000,
          "cb_option": 0,
          "sold": 190,
          "stock": 27,
          "status": 1,
          "price_max": 137900000,
          "add_on_deal_info": {
            "add_on_deal_id": 1905420,
            "add_on_deal_label": "Add-on Deal",
            "sub_type": 0
          },
          "is_group_buy_item": null,
          "flash_sale": null,
          "price": 107900000,
          "shop_location": "Singapore",
          "item_rating": {
            "rating_star": 4.883392,
            "rating_count": [
              283,
              3,
              2,
              3,
              9,
              266
            ],
            "rcount_with_image": 134,
            "rcount_with_context": 189
          },
          "show_official_shop_label_in_title": false,
          "tier_variations": [
            {
              "images": [
                "071f8dc4b7cbab70f6b7c020ddc275eb",
                "b4c32ecfe564da47e6bbf7665eb4f16c",
                "df4fb0c1f695b07e371d8828253419d6",
                "cae4223126fd9c2eca7d16a02619b273",
                "8ab6fa63776d0e4eb4252261c3b753a7"
              ],
              "properties": [],
              "type": 0,
              "name": "Colors",
              "options": [
                "White",
                "Black",
                "Blue",
                "Green",
                "(PRODUCT)RED"
              ]
            },
            {
              "images": [],
              "properties": [],
              "type": 0,
              "name": "Capacity",
              "options": [
                "64GB",
                "128GB",
                "256GB"
              ]
            }
          ],
          "is_adult": false,
          "can_use_cod": null,
          "discount": "17%",
          "flag": 524288,
          "is_non_cc_installment_payment_eligible": false,
          "has_lowest_price_guarantee": false,
          "has_group_buy_stock": null,
          "preview_info": null,
          "welcome_package_type": 0,
          "exclusive_price_info": null,
          "name": "2020 Apple iPhone 12 64GB | 128GB | 256GB",
          "ctime": 1602672750,
          "wholesale_tier_list": [],
          "show_shopee_verified_label": true,
          "show_official_shop_label_in_normal_position": null,
          "item_status": "normal",
          "shopee_verified": true,
          "hidden_price_display": null,
          "size_chart": null,
          "item_type": 0,
          "shipping_icon_type": null,
          "label_ids": [
            1000012,
            1000055,
            1000035,
            1001261
          ],
          "service_by_shopee_flag": null,
          "badge_icon_type": 0,
          "historical_sold": 682,
          "transparent_background_image": ""
        },
        {
          "itemid": 4708450478,
          "welcome_package_info": null,
          "liked": null,
          "recommendation_info": null,
          "bundle_deal_info": null,
          "price_max_before_discount": 9590000,
          "image": "628c1908fd7e4fa5d22ec0b482cc6ac8",
          "recommendation_algorithm": null,
          "is_cc_installment_payment_eligible": false,
          "shopid": 202818022,
          "can_use_wholesale": false,
          "group_buy_info": null,
          "reference_item_id": "",
          "currency": "SGD",
          "raw_discount": 8,
          "show_free_shipping": false,
          "video_info_list": [
            {
              "duration": 20,
              "video_id": "a156dc2281511a6d1a840de049f2400b",
              "version": 1,
              "thumb_url": "4112a0db13f6ededb13aada287680d91"
            }
          ],
          "images": [
            "628c1908fd7e4fa5d22ec0b482cc6ac8",
            "43c31bbc2509bad0507bc2df9259cc7a",
            "e83c65477bccdd30ed62c939984f32b0",
            "d6ebd99d48a0adc271e3d0776af818a9",
            "c24d9ebdb319eb84b2df050e2fd8d8dd",
            "a768000f46f8628e72463eefebf6bbf8",
            "cea494468ac6927befd24b7e4e5b62ce",
            "6f60f4438a5e9a524108504e4a0d6f05"
          ],
          "is_preferred_plus_seller": false,
          "price_before_discount": 9590000,
          "is_category_failed": false,
          "show_discount": 8,
          "cmt_count": 6850,
          "view_count": 37606,
          "catid": 2414,
          "voucher_info": null,
          "upcoming_flash_sale": null,
          "is_official_shop": true,
          "brand": "Airbot",
          "price_min": 8790000,
          "liked_count": 9943,
          "can_use_bundle_deal": false,
          "show_official_shop_label": true,
          "coin_earn_label": null,
          "price_min_before_discount": 9590000,
          "cb_option": 0,
          "sold": 1100,
          "stock": 238,
          "status": 1,
          "price_max": 8790000,
          "add_on_deal_info": null,
          "is_group_buy_item": null,
          "flash_sale": null,
          "price": 8790000,
          "shop_location": "Singapore",
          "item_rating": {
            "rating_star": 4.922583,
            "rating_count": [
              6846,
              10,
              11,
              64,
              329,
              6432
            ],
            "rcount_with_image": 2617,
            "rcount_with_context": 4164
          },
          "show_official_shop_label_in_title": true,
          "tier_variations": [
            {
              "images": [],
              "properties": [],
              "type": 0,
              "name": "Color",
              "options": [
                "Red"
              ]
            },
            {
              "images": [],
              "properties": [],
              "type": 0,
              "name": "Warrranty",
              "options": [
                "12 Months"
              ]
            }
          ],
          "is_adult": false,
          "can_use_cod": null,
          "discount": "8%",
          "flag": 0,
          "is_non_cc_installment_payment_eligible": false,
          "has_lowest_price_guarantee": false,
          "has_group_buy_stock": null,
          "preview_info": null,
          "welcome_package_type": 0,
          "exclusive_price_info": null,
          "name": "Airbot Supersonics 2.0 (Red) Cordless Stick Vacuum Cyclone Boost Handheld Vacuum Cleaner",
          "ctime": 1574669896,
          "wholesale_tier_list": [],
          "show_shopee_verified_label": false,
          "show_official_shop_label_in_normal_position": null,
          "item_status": "normal",
          "shopee_verified": false,
          "hidden_price_display": null,
          "size_chart": null,
          "item_type": 0,
          "shipping_icon_type": null,
          "label_ids": [
            1000010,
            1000012,
            22,
            1001244,
            1001954,
            1002448,
            1000055,
            1003124,
            1003208,
            1000035,
            1000065,
            1000067,
            1000077,
            1000094,
            13,
            1001261
          ],
          "service_by_shopee_flag": null,
          "badge_icon_type": 0,
          "historical_sold": 13586,
          "transparent_background_image": "058a7c77b0a60a59e2335e2cbb8b07fe"
        },
        {
          "itemid": 6731444734,
          "welcome_package_info": null,
          "liked": null,
          "recommendation_info": null,
          "bundle_deal_info": null,
          "price_max_before_discount": 323800000,
          "image": "8e360e47bde2b36d1737fd42e67827c6",
          "recommendation_algorithm": null,
          "is_cc_installment_payment_eligible": true,
          "shopid": 251249431,
          "can_use_wholesale": false,
          "group_buy_info": null,
          "reference_item_id": "",
          "currency": "SGD",
          "raw_discount": 11,
          "show_free_shipping": false,
          "video_info_list": [],
          "images": [
            "8e360e47bde2b36d1737fd42e67827c6",
            "f8569403aa72d96b18b08a4ea7201b3b"
          ],
          "is_preferred_plus_seller": false,
          "price_before_discount": 132800000,
          "is_category_failed": false,
          "show_discount": 11,
          "cmt_count": 37,
          "view_count": 1763,
          "catid": 2414,
          "voucher_info": null,
          "upcoming_flash_sale": null,
          "is_official_shop": false,
          "brand": "",
          "price_min": 120800000,
          "liked_count": 122,
          "can_use_bundle_deal": false,
          "show_official_shop_label": false,
          "coin_earn_label": null,
          "price_min_before_discount": 132800000,
          "cb_option": 0,
          "sold": 4,
          "stock": 28,
          "status": 1,
          "price_max": 293800000,
          "add_on_deal_info": null,
          "is_group_buy_item": null,
          "flash_sale": null,
          "price": 120800000,
          "shop_location": "Singapore",
          "item_rating": {
            "rating_star": 4.972973,
            "rating_count": [
              37,
              0,
              0,
              0,
              1,
              36
            ],
            "rcount_with_image": 18,
            "rcount_with_context": 34
          },
          "show_official_shop_label_in_title": false,
          "tier_variations": [
            {
              "images": [],
              "properties": [],
              "type": 0,
              "name": "Size",
              "options": [
                "55”",
                "65”",
                "75”",
                "82”"
              ]
            },
            {
              "images": [],
              "properties": [],
              "type": 0,
              "name": "Mounting",
              "options": [
                "TV stands",
                "Fixed bracket",
                "Swivel"
              ]
            }
          ],
          "is_adult": false,
          "can_use_cod": null,
          "discount": "11%",
          "flag": 524288,
          "is_non_cc_installment_payment_eligible": false,
          "has_lowest_price_guarantee": false,
          "has_group_buy_stock": null,
          "preview_info": null,
          "welcome_package_type": 0,
          "exclusive_price_info": null,
          "name": "2019 Samsung QLED Q70R 4K TV",
          "ctime": 1587757721,
          "wholesale_tier_list": [],
          "show_shopee_verified_label": false,
          "show_official_shop_label_in_normal_position": null,
          "item_status": "normal",
          "shopee_verified": false,
          "hidden_price_display": null,
          "size_chart": null,
          "item_type": 0,
          "shipping_icon_type": null,
          "label_ids": [
            22,
            1000010,
            1000012,
            1000107,
            1000055,
            1003124,
            1003208,
            1000035,
            1000088,
            1000094,
            13,
            1001261,
            1001268
          ],
          "service_by_shopee_flag": null,
          "badge_icon_type": 0,
          "historical_sold": 79,
          "transparent_background_image": "6624276f55c4026611b4ddb34237302f"
        },
        {
          "itemid": 7162310254,
          "welcome_package_info": null,
          "liked": null,
          "recommendation_info": null,
          "bundle_deal_info": null,
          "price_max_before_discount": 14800000,
          "image": "be6ebc46c7d7e23c25dbb5cdd8c86fcd",
          "recommendation_algorithm": null,
          "is_cc_installment_payment_eligible": false,
          "shopid": 21030308,
          "can_use_wholesale": false,
          "group_buy_info": null,
          "reference_item_id": "",
          "currency": "SGD",
          "raw_discount": 20,
          "show_free_shipping": false,
          "video_info_list": [],
          "images": [
            "be6ebc46c7d7e23c25dbb5cdd8c86fcd"
          ],
          "is_preferred_plus_seller": false,
          "price_before_discount": 14800000,
          "is_category_failed": false,
          "show_discount": 20,
          "cmt_count": 55,
          "view_count": 1951,
          "catid": 8,
          "voucher_info": null,
          "upcoming_flash_sale": null,
          "is_official_shop": false,
          "brand": "Huawei",
          "price_min": 11900000,
          "liked_count": 97,
          "can_use_bundle_deal": false,
          "show_official_shop_label": false,
          "coin_earn_label": null,
          "price_min_before_discount": 14800000,
          "cb_option": 0,
          "sold": 14,
          "stock": 244,
          "status": 1,
          "price_max": 11900000,
          "add_on_deal_info": null,
          "is_group_buy_item": null,
          "flash_sale": null,
          "price": 11900000,
          "shop_location": "Singapore",
          "item_rating": {
            "rating_star": 4.909091,
            "rating_count": [
              55,
              1,
              0,
              0,
              1,
              53
            ],
            "rcount_with_image": 19,
            "rcount_with_context": 31
          },
          "show_official_shop_label_in_title": false,
          "tier_variations": [
            {
              "images": [],
              "properties": [],
              "type": 0,
              "name": "Colour",
              "options": [
                "Graphite",
                "Mint Green",
                "Sakura Pink "
              ]
            }
          ],
          "is_adult": false,
          "can_use_cod": null,
          "discount": "20%",
          "flag": 0,
          "is_non_cc_installment_payment_eligible": false,
          "has_lowest_price_guarantee": false,
          "has_group_buy_stock": null,
          "preview_info": null,
          "welcome_package_type": 0,
          "exclusive_price_info": null,
          "name": "3.3 SALES - Huawei Watch Fit (Local Set)",
          "ctime": 1605089104,
          "wholesale_tier_list": [],
          "show_shopee_verified_label": true,
          "show_official_shop_label_in_normal_position": null,
          "item_status": "normal",
          "shopee_verified": true,
          "hidden_price_display": null,
          "size_chart": null,
          "item_type": 0,
          "shipping_icon_type": null,
          "label_ids": [
            1000012,
            1001954,
            1000055,
            1001261,
            1000035
          ],
          "service_by_shopee_flag": null,
          "badge_icon_type": 0,
          "historical_sold": 163,
          "transparent_background_image": "2110b784b1328b900150c4653dcf6406"
        },
        {
          "itemid": 1515303086,
          "welcome_package_info": null,
          "liked": null,
          "recommendation_info": null,
          "bundle_deal_info": null,
          "price_max_before_discount": 3850000,
          "image": "940d912312eba641ac110a0238f1ab08",
          "recommendation_algorithm": null,
          "is_cc_installment_payment_eligible": false,
          "shopid": 91242967,
          "can_use_wholesale": false,
          "group_buy_info": null,
          "reference_item_id": "",
          "currency": "SGD",
          "raw_discount": 10,
          "show_free_shipping": false,
          "video_info_list": [],
          "images": [
            "940d912312eba641ac110a0238f1ab08",
            "ae9a49fea288dafa8c7dde819a4d4b10",
            "a43d76e13c8695f8522f630c73695154",
            "debb3404964fa7d11886b6972e2a2b89"
          ],
          "is_preferred_plus_seller": false,
          "price_before_discount": 3790000,
          "is_category_failed": false,
          "show_discount": 10,
          "cmt_count": 15705,
          "view_count": 38060,
          "catid": 12,
          "voucher_info": null,
          "upcoming_flash_sale": null,
          "is_official_shop": false,
          "brand": "Merries",
          "price_min": 3450000,
          "liked_count": 3746,
          "can_use_bundle_deal": false,
          "show_official_shop_label": false,
          "coin_earn_label": null,
          "price_min_before_discount": 3790000,
          "cb_option": 0,
          "sold": 6623,
          "stock": 3297,
          "status": 1,
          "price_max": 3450000,
          "add_on_deal_info": {
            "add_on_deal_id": 1840945,
            "add_on_deal_label": "Add-on Deal",
            "sub_type": 0
          },
          "is_group_buy_item": null,
          "flash_sale": null,
          "price": 3450000,
          "shop_location": "Singapore",
          "item_rating": {
            "rating_star": 4.946245,
            "rating_count": [
              15707,
              67,
              44,
              90,
              285,
              15221
            ],
            "rcount_with_image": 5247,
            "rcount_with_context": 8710
          },
          "show_official_shop_label_in_title": false,
          "tier_variations": [
            {
              "images": [
                "28f1d5efe0c384b9d8a7ce3efc2331c5",
                "3f538e911d760506ed3598cdd2c09b61",
                "9fd5e16a5b2487dcb5b29fcf283629b9",
                "9cce8417ab7d242d3f1752d61463acda",
                "43e2ae928d2542f1f10111482b71c836",
                "401e521d5a9fdb6caf265fb5f63955ed",
                "55b04564265863e68bbe31d842b505ea",
                "ed0594018c05d35d66a39a1c76701b4c"
              ],
              "properties": [],
              "type": 0,
              "name": "Merries Diaper",
              "options": [
                "TAPE NB96 x 2",
                " TAPE S88 x 2",
                " TAPE M68 x 2",
                " TAPE L58 x 2",
                "PANTS M64 x 2",
                "PANTS  L50 x 2",
                "PANTS XL44 x 2",
                "PANTS XXL28 x 2"
              ]
            }
          ],
          "is_adult": false,
          "can_use_cod": null,
          "discount": "10%",
          "flag": 0,
          "is_non_cc_installment_payment_eligible": false,
          "has_lowest_price_guarantee": false,
          "has_group_buy_stock": null,
          "preview_info": null,
          "welcome_package_type": 0,
          "exclusive_price_info": null,
          "name": "<READY FOR STOCK> MERRIES Giant pack Sale/all size available",
          "ctime": 1537522509,
          "wholesale_tier_list": [],
          "show_shopee_verified_label": false,
          "show_official_shop_label_in_normal_position": null,
          "item_status": "normal",
          "shopee_verified": false,
          "hidden_price_display": null,
          "size_chart": null,
          "item_type": 0,
          "shipping_icon_type": null,
          "label_ids": [
            1000055,
            1000035,
            13,
            1001261
          ],
          "service_by_shopee_flag": null,
          "badge_icon_type": 0,
          "historical_sold": 58450,
          "transparent_background_image": "940d912312eba641ac110a0238f1ab08"
        },
        {
          "itemid": 452829016,
          "welcome_package_info": null,
          "liked": null,
          "recommendation_info": null,
          "bundle_deal_info": null,
          "price_max_before_discount": 12700000,
          "image": "fe755ac92ebd2b58300317d66d79438a",
          "recommendation_algorithm": null,
          "is_cc_installment_payment_eligible": false,
          "shopid": 27998060,
          "can_use_wholesale": false,
          "group_buy_info": null,
          "reference_item_id": "",
          "currency": "SGD",
          "raw_discount": 47,
          "show_free_shipping": false,
          "video_info_list": [],
          "images": [
            "fe755ac92ebd2b58300317d66d79438a",
            "86851c19a30ac6baa430a75cc976d34e",
            "35490f11632dfd9e83be6f67cef749fc"
          ],
          "is_preferred_plus_seller": false,
          "price_before_discount": 12700000,
          "is_category_failed": false,
          "show_discount": 47,
          "cmt_count": 49,
          "view_count": 1151,
          "catid": 6,
          "voucher_info": null,
          "upcoming_flash_sale": null,
          "is_official_shop": true,
          "brand": "Lancome",
          "price_min": 6690000,
          "liked_count": 126,
          "can_use_bundle_deal": false,
          "show_official_shop_label": true,
          "coin_earn_label": null,
          "price_min_before_discount": 12700000,
          "cb_option": 1,
          "sold": 10,
          "stock": 417,
          "status": 1,
          "price_max": 6690000,
          "add_on_deal_info": null,
          "is_group_buy_item": null,
          "flash_sale": null,
          "price": 6690000,
          "shop_location": "Hong Kong",
          "item_rating": {
            "rating_star": 4.816327,
            "rating_count": [
              49,
              0,
              0,
              1,
              7,
              41
            ],
            "rcount_with_image": 21,
            "rcount_with_context": 28
          },
          "show_official_shop_label_in_title": true,
          "tier_variations": [
            {
              "images": [],
              "properties": [],
              "type": 0,
              "name": "",
              "options": [
                ""
              ]
            }
          ],
          "is_adult": false,
          "can_use_cod": null,
          "discount": "47%",
          "flag": 0,
          "is_non_cc_installment_payment_eligible": false,
          "has_lowest_price_guarantee": false,
          "has_group_buy_stock": null,
          "preview_info": null,
          "welcome_package_type": 0,
          "exclusive_price_info": null,
          "name": "Lancome Advanced Genifique Eye Youth Activate. Conc. 20ml",
          "ctime": 1504145219,
          "wholesale_tier_list": [],
          "show_shopee_verified_label": false,
          "show_official_shop_label_in_normal_position": null,
          "item_status": "normal",
          "shopee_verified": false,
          "hidden_price_display": null,
          "size_chart": null,
          "item_type": 0,
          "shipping_icon_type": null,
          "label_ids": [
            22,
            1000007,
            1000020,
            1000029,
            1000024,
            1000010,
            1001244,
            1000065,
            1000067,
            1001261,
            1000035,
            1000094,
            1001606
          ],
          "service_by_shopee_flag": null,
          "badge_icon_type": 0,
          "historical_sold": 131,
          "transparent_background_image": "fe755ac92ebd2b58300317d66d79438a"
        },
        {
          "itemid": 215377534,
          "welcome_package_info": null,
          "liked": null,
          "recommendation_info": null,
          "bundle_deal_info": null,
          "price_max_before_discount": 11980000,
          "image": "1899f570a59e442c2c358a3191398a81",
          "recommendation_algorithm": null,
          "is_cc_installment_payment_eligible": false,
          "shopid": 640697,
          "can_use_wholesale": false,
          "group_buy_info": null,
          "reference_item_id": "",
          "currency": "SGD",
          "raw_discount": 57,
          "show_free_shipping": true,
          "video_info_list": [],
          "images": [
            "1899f570a59e442c2c358a3191398a81",
            "c696bc5e2b33ebe4b5590a429c4c8d5f",
            "36283b98ee714083ae943b34f584fe4a",
            "25036b468eb52262c577df23e21040bf",
            "6630ddf1cfe41b8a903f3a41e3729572",
            "c8fc93438d30d3a21689cbca7498e1de",
            "62d23b07466ecdb77ced33a2f9df5f98",
            "f3d75fcc3a458a279a7eb47ff91aa128"
          ],
          "is_preferred_plus_seller": false,
          "price_before_discount": 5990000,
          "is_category_failed": false,
          "show_discount": 57,
          "cmt_count": 2514,
          "view_count": 13741,
          "catid": 16997,
          "voucher_info": null,
          "upcoming_flash_sale": null,
          "is_official_shop": true,
          "brand": "Kinohimitsu",
          "price_min": 3390000,
          "liked_count": 1845,
          "can_use_bundle_deal": false,
          "show_official_shop_label": true,
          "coin_earn_label": null,
          "price_min_before_discount": 5990000,
          "cb_option": 0,
          "sold": 367,
          "stock": 352,
          "status": 1,
          "price_max": 5200000,
          "add_on_deal_info": null,
          "is_group_buy_item": null,
          "flash_sale": null,
          "price": 3390000,
          "shop_location": "Singapore",
          "item_rating": {
            "rating_star": 4.939539,
            "rating_count": [
              2514,
              6,
              0,
              31,
              66,
              2411
            ],
            "rcount_with_image": 961,
            "rcount_with_context": 1358
          },
          "show_official_shop_label_in_title": true,
          "tier_variations": [
            {
              "images": [
                "4cc38a92bac54378512c924542f1202f",
                "61a2d440947621117965d1de1f671919"
              ],
              "properties": [],
              "type": 0,
              "name": "Choice",
              "options": [
                "Enzyme 30s (1BOX)",
                "Enzyme30sx2 (2BOXES)"
              ]
            }
          ],
          "is_adult": false,
          "can_use_cod": null,
          "discount": "57%",
          "flag": 2,
          "is_non_cc_installment_payment_eligible": false,
          "has_lowest_price_guarantee": false,
          "has_group_buy_stock": null,
          "preview_info": null,
          "welcome_package_type": 0,
          "exclusive_price_info": null,
          "name": "[Bundle of 2] Kinohimitsu Detox Enzyme 30's",
          "ctime": 1491898322,
          "wholesale_tier_list": [],
          "show_shopee_verified_label": false,
          "show_official_shop_label_in_normal_position": null,
          "item_status": "normal",
          "shopee_verified": false,
          "hidden_price_display": null,
          "size_chart": null,
          "item_type": 0,
          "shipping_icon_type": null,
          "label_ids": [
            22,
            1000021,
            1000012,
            1000010,
            1001244,
            1001954,
            1002448,
            1000055,
            1003208,
            1000018,
            1000030,
            1000035,
            1000052,
            1000065,
            1000067,
            1000094,
            13,
            21,
            1001261
          ],
          "service_by_shopee_flag": null,
          "badge_icon_type": 0,
          "historical_sold": 6477,
          "transparent_background_image": "885031c3349445f74f09dbed7219501f"
        },
        {
          "itemid": 4026603913,
          "welcome_package_info": null,
          "liked": null,
          "recommendation_info": null,
          "bundle_deal_info": null,
          "price_max_before_discount": 39900000,
          "image": "977f1c23599102f8923f6d5718ea3028",
          "recommendation_algorithm": null,
          "is_cc_installment_payment_eligible": true,
          "shopid": 21030308,
          "can_use_wholesale": false,
          "group_buy_info": null,
          "reference_item_id": "",
          "currency": "SGD",
          "raw_discount": 21,
          "show_free_shipping": false,
          "video_info_list": [],
          "images": [
            "977f1c23599102f8923f6d5718ea3028"
          ],
          "is_preferred_plus_seller": false,
          "price_before_discount": 39900000,
          "is_category_failed": false,
          "show_discount": 21,
          "cmt_count": 281,
          "view_count": 1460,
          "catid": 8,
          "voucher_info": null,
          "upcoming_flash_sale": null,
          "is_official_shop": false,
          "brand": "Mediapad M5",
          "price_min": 31500000,
          "liked_count": 319,
          "can_use_bundle_deal": false,
          "show_official_shop_label": false,
          "coin_earn_label": null,
          "price_min_before_discount": 39900000,
          "cb_option": 0,
          "sold": 23,
          "stock": 745,
          "status": 1,
          "price_max": 31500000,
          "add_on_deal_info": null,
          "is_group_buy_item": null,
          "flash_sale": null,
          "price": 31500000,
          "shop_location": "Singapore",
          "item_rating": {
            "rating_star": 4.935943,
            "rating_count": [
              281,
              0,
              0,
              1,
              16,
              264
            ],
            "rcount_with_image": 124,
            "rcount_with_context": 190
          },
          "show_official_shop_label_in_title": false,
          "tier_variations": [
            {
              "images": [],
              "properties": [],
              "type": 0,
              "name": "Color",
              "options": [
                "Grey"
              ]
            }
          ],
          "is_adult": false,
          "can_use_cod": null,
          "discount": "21%",
          "flag": 524288,
          "is_non_cc_installment_payment_eligible": false,
          "has_lowest_price_guarantee": false,
          "has_group_buy_stock": null,
          "preview_info": null,
          "welcome_package_type": 0,
          "exclusive_price_info": null,
          "name": "3.3 SALES - Huawei Mediapad M5 Lite LTE + FREE Flip Folder (Local Set)",
          "ctime": 1586614674,
          "wholesale_tier_list": [],
          "show_shopee_verified_label": true,
          "show_official_shop_label_in_normal_position": null,
          "item_status": "normal",
          "shopee_verified": true,
          "hidden_price_display": null,
          "size_chart": null,
          "item_type": 0,
          "shipping_icon_type": null,
          "label_ids": [
            1000012,
            1001954,
            1000055,
            1000035,
            1000075,
            1000092,
            13,
            1001261,
            1001268
          ],
          "service_by_shopee_flag": null,
          "badge_icon_type": 0,
          "historical_sold": 667,
          "transparent_background_image": "a0d602eb0e8f0ce267aaa31b951f9c6e"
        }
      ],
      "price_text_color": "#000000",
      "section_background_color": null,
      "header_text": "MEGA SPREE DEALS",
      "see_more_link": "https://shopee.sg/m/3-3-mdd-mega-spree#megaspreedeals",
      "banner_image": null
    },
    "campaign_top_visual": {
      "start": 1613923200,
      "end": 1645113600,
      "banner_image": "dab07029f5c1606fc75d7a404d743168",
      "data": {
        "image_mobile": "dab07029f5c1606fc75d7a404d743168",
        "image_ratio_pc": 20,
        "image_ratio": 3.061224,
        "image_pc": "18c3a7712106272165bd8281707f5a03"
      }
    },
    "campaign_images": {
      "start": 1608998400,
      "end": 1641225600,
      "banner_image": null,
      "data": {
        "image_pc": "ab28520a348e455dfb0f354b8fc5d35f",
        "one_row_image": "9ccf6e7f8dd144b88e51c743c6d284cb",
        "two_row_image": "876403c154e99cb16dbe97db7704b818"
      }
    },
    "featured_collections": null
  },
  "error_msg": null,
  "error": null
}
